{
  "id": "akutagawa",
  "title": "芥川",
  "source": "伊勢物語",
  "genre": "古文",
  "sections": [
    {
      "id": "s1",
      "title": "第一段",
      "text": "昔、男ありけり。女のえ得まじかりけるを、\n年を経てよばひわたりけるを、からうじて\n盗み出でて、いと暗きに来けり。\n芥川といふ川を率て行きければ、\n草の上に置きたりける露を、\n「かれは何ぞ。」となむ男に問ひける。\n行く先多く、夜も更けにければ、\n鬼ある所とも知らで、\n神さへいといみじう鳴り、\n雨もいたう降りければ、\nあばらなる蔵に、女をば奥に押し入れて、\n男、弓・胡籙を負ひて戸口に居り。",
      "modern": "昔、男がいた。女で手に入れることができそうになかった女を、長年にわたって求婚し続けていたが、やっとのことで盗み出して、とても暗いときに逃げて来た。芥川という川（のほとり）を（女を）連れて行ったところ、草の上に降りていた夜露を、「あれは何ですか。」と（女は）男に尋ねた。行く先が遠く、夜も更けてしまったので、鬼が棲むところとも知らないで、そのうえ雷までもたいそうひどく鳴り、雨も激しく降ったので、荒れてがらんとした蔵に、女を奥の方に押し入れて、男は、弓・胡籙を背負って戸口にいる。",
      "notes": "",
      "targets": [
        {
          "id": "verb-s1-1",
          "type": "verb",
          "surface": "あり",
          "answer": "ラ行変格活用・連用形",
          "explanation": "ラ行変格活用・連用形",
          "start": 3,
          "end": 5,
          "conjugationType": "ラ行変格活用",
          "formInText": "連用形",
          "sectionId": "s1"
        },
        {
          "id": "aux-s1-1",
          "type": "aux",
          "surface": "けり",
          "answer": "過去の助動詞・終止形",
          "explanation": "過去の助動詞・終止形",
          "start": 5,
          "end": 7,
          "formInText": "終止形",
          "sectionId": "s1"
        },
        {
          "id": "particle-s1-1",
          "type": "particle",
          "surface": "の",
          "answer": "格助詞（同格）",
          "explanation": "格助詞（同格）",
          "start": 9,
          "end": 10,
          "particleQuestionType": "translation",
          "sectionId": "s1"
        },
        {
          "id": "vocab-s1-1",
          "type": "vocab",
          "surface": "え",
          "answer": "副詞",
          "explanation": "副詞",
          "start": 10,
          "end": 11,
          "sectionId": "s1"
        },
        {
          "id": "verb-s1-2",
          "type": "verb",
          "surface": "得",
          "answer": "ア行下二段活用・終止形",
          "explanation": "ア行下二段活用・終止形",
          "start": 11,
          "end": 12,
          "conjugationType": "ア行下二段活用",
          "formInText": "終止形",
          "sectionId": "s1"
        },
        {
          "id": "aux-s1-2",
          "type": "aux",
          "surface": "まじかり",
          "answer": "打消推量の助動詞・連用形",
          "explanation": "打消推量の助動詞・連用形",
          "start": 12,
          "end": 16,
          "formInText": "連用形",
          "sectionId": "s1"
        },
        {
          "id": "aux-s1-3",
          "type": "aux",
          "surface": "ける",
          "answer": "過去の助動詞・連体形",
          "explanation": "過去の助動詞・連体形",
          "start": 16,
          "end": 18,
          "formInText": "連体形",
          "sectionId": "s1"
        },
        {
          "id": "particle-s1-2",
          "type": "particle",
          "surface": "を",
          "answer": "格助詞（対象）",
          "explanation": "格助詞（対象）",
          "start": 18,
          "end": 19,
          "particleQuestionType": "translation",
          "sectionId": "s1"
        },
        {
          "id": "particle-s1-3",
          "type": "particle",
          "surface": "を",
          "answer": "格助詞（時）",
          "explanation": "格助詞（時）",
          "start": 22,
          "end": 23,
          "particleQuestionType": "translation",
          "sectionId": "s1"
        },
        {
          "id": "verb-s1-3",
          "type": "verb",
          "surface": "経",
          "answer": "ハ行下二段活用・連用形",
          "explanation": "ハ行下二段活用・連用形",
          "start": 23,
          "end": 24,
          "conjugationType": "ハ行下二段活用",
          "formInText": "連用形",
          "sectionId": "s1"
        },
        {
          "id": "particle-s1-4",
          "type": "particle",
          "surface": "て",
          "answer": "接続助詞（単純）",
          "explanation": "接続助詞（単純）",
          "start": 24,
          "end": 25,
          "particleQuestionType": "translation",
          "sectionId": "s1"
        },
        {
          "id": "verb-s1-4",
          "type": "verb",
          "surface": "よばひ",
          "answer": "ハ行四段活用・連用形",
          "explanation": "ハ行四段活用・連用形",
          "start": 25,
          "end": 28,
          "conjugationType": "ハ行四段活用",
          "formInText": "連用形",
          "sectionId": "s1"
        },
        {
          "id": "verb-s1-5",
          "type": "verb",
          "surface": "わたり",
          "answer": "ラ行四段活用・連用形",
          "explanation": "ラ行四段活用・連用形",
          "start": 28,
          "end": 31,
          "conjugationType": "ラ行四段活用",
          "formInText": "連用形",
          "sectionId": "s1"
        },
        {
          "id": "aux-s1-4",
          "type": "aux",
          "surface": "ける",
          "answer": "過去の助動詞・連体形",
          "explanation": "過去の助動詞・連体形",
          "start": 31,
          "end": 33,
          "formInText": "連体形",
          "sectionId": "s1"
        },
        {
          "id": "particle-s1-5",
          "type": "particle",
          "surface": "を",
          "answer": "接続助詞（単純）",
          "explanation": "接続助詞（単純）",
          "start": 33,
          "end": 34,
          "particleQuestionType": "translation",
          "sectionId": "s1"
        },
        {
          "id": "vocab-s1-2",
          "type": "vocab",
          "surface": "からうじて",
          "answer": "副詞",
          "explanation": "副詞",
          "start": 35,
          "end": 40,
          "sectionId": "s1"
        },
        {
          "id": "verb-s1-6",
          "type": "verb",
          "surface": "盗み",
          "answer": "マ行四段活用・連用形",
          "explanation": "マ行四段活用・連用形",
          "start": 41,
          "end": 43,
          "conjugationType": "マ行四段活用",
          "formInText": "連用形",
          "sectionId": "s1"
        },
        {
          "id": "verb-s1-7",
          "type": "verb",
          "surface": "出で",
          "answer": "ダ行下二段活用・連用形",
          "explanation": "ダ行下二段活用・連用形",
          "start": 43,
          "end": 45,
          "conjugationType": "ダ行下二段活用",
          "formInText": "連用形",
          "sectionId": "s1"
        },
        {
          "id": "particle-s1-6",
          "type": "particle",
          "surface": "て",
          "answer": "接続助詞（単純）",
          "explanation": "接続助詞（単純）",
          "start": 39,
          "end": 40,
          "particleQuestionType": "translation",
          "sectionId": "s1"
        },
        {
          "id": "vocab-s1-3",
          "type": "vocab",
          "surface": "いと",
          "answer": "副詞",
          "explanation": "副詞",
          "start": 47,
          "end": 49,
          "sectionId": "s1"
        },
        {
          "id": "adj-s1-1",
          "type": "adj",
          "surface": "暗き",
          "answer": "ク活用形容詞・連体形",
          "explanation": "ク活用形容詞・連体形",
          "start": 49,
          "end": 51,
          "conjugationType": "ク活用形容詞",
          "formInText": "連体形",
          "sectionId": "s1"
        },
        {
          "id": "particle-s1-7",
          "type": "particle",
          "surface": "に",
          "answer": "格助詞（時）",
          "explanation": "格助詞（時）",
          "start": 51,
          "end": 52,
          "particleQuestionType": "translation",
          "sectionId": "s1"
        },
        {
          "id": "verb-s1-8",
          "type": "verb",
          "surface": "来",
          "answer": "カ行変格活用・連用形",
          "explanation": "カ行変格活用・連用形",
          "start": 52,
          "end": 53,
          "conjugationType": "カ行変格活用",
          "formInText": "連用形",
          "sectionId": "s1"
        },
        {
          "id": "aux-s1-5",
          "type": "aux",
          "surface": "けり",
          "answer": "過去の助動詞・終止形",
          "explanation": "過去の助動詞・終止形",
          "start": 53,
          "end": 55,
          "formInText": "終止形",
          "sectionId": "s1"
        },
        {
          "id": "particle-s1-8",
          "type": "particle",
          "surface": "と",
          "answer": "格助詞（引用）",
          "explanation": "格助詞（引用）",
          "start": 48,
          "end": 49,
          "particleQuestionType": "translation",
          "sectionId": "s1"
        },
        {
          "id": "verb-s1-9",
          "type": "verb",
          "surface": "いふ",
          "answer": "ハ行四段活用・連体形",
          "explanation": "ハ行四段活用・連体形",
          "start": 60,
          "end": 62,
          "conjugationType": "ハ行四段活用",
          "formInText": "連体形",
          "sectionId": "s1"
        },
        {
          "id": "particle-s1-9",
          "type": "particle",
          "surface": "を",
          "answer": "格助詞（場所）",
          "explanation": "格助詞（場所）",
          "start": 63,
          "end": 64,
          "particleQuestionType": "translation",
          "sectionId": "s1"
        },
        {
          "id": "verb-s1-10",
          "type": "verb",
          "surface": "率",
          "answer": "ワ行上一段活用・連用形",
          "explanation": "ワ行上一段活用・連用形",
          "start": 64,
          "end": 65,
          "conjugationType": "ワ行上一段活用",
          "formInText": "連用形",
          "sectionId": "s1"
        },
        {
          "id": "particle-s1-10",
          "type": "particle",
          "surface": "て",
          "answer": "接続助詞（単純）",
          "explanation": "接続助詞（単純）",
          "start": 45,
          "end": 46,
          "particleQuestionType": "translation",
          "sectionId": "s1"
        },
        {
          "id": "verb-s1-11",
          "type": "verb",
          "surface": "行き",
          "answer": "カ行四段活用・連用形",
          "explanation": "カ行四段活用・連用形",
          "start": 66,
          "end": 68,
          "conjugationType": "カ行四段活用",
          "formInText": "連用形",
          "sectionId": "s1"
        },
        {
          "id": "aux-s1-6",
          "type": "aux",
          "surface": "けれ",
          "answer": "過去の助動詞・已然形",
          "explanation": "過去の助動詞・已然形",
          "start": 68,
          "end": 70,
          "formInText": "已然形",
          "sectionId": "s1"
        },
        {
          "id": "particle-s1-11",
          "type": "particle",
          "surface": "ば",
          "answer": "接続助詞（順確偶然）",
          "explanation": "接続助詞（順確偶然）",
          "start": 26,
          "end": 27,
          "particleQuestionType": "translation",
          "sectionId": "s1"
        },
        {
          "id": "particle-s1-12",
          "type": "particle",
          "surface": "の",
          "answer": "格助詞（連体）",
          "explanation": "格助詞（連体）",
          "start": 74,
          "end": 75,
          "particleQuestionType": "translation",
          "sectionId": "s1"
        },
        {
          "id": "particle-s1-13",
          "type": "particle",
          "surface": "に",
          "answer": "格助詞（場所）",
          "explanation": "格助詞（場所）",
          "start": 76,
          "end": 77,
          "particleQuestionType": "translation",
          "sectionId": "s1"
        },
        {
          "id": "verb-s1-12",
          "type": "verb",
          "surface": "置き",
          "answer": "カ行四段活用・連用形",
          "explanation": "カ行四段活用・連用形",
          "start": 77,
          "end": 79,
          "conjugationType": "カ行四段活用",
          "formInText": "連用形",
          "sectionId": "s1"
        },
        {
          "id": "aux-s1-7",
          "type": "aux",
          "surface": "たり",
          "answer": "存続の助動詞・連用形",
          "explanation": "存続の助動詞・連用形",
          "start": 29,
          "end": 31,
          "formInText": "連用形",
          "sectionId": "s1"
        },
        {
          "id": "aux-s1-8",
          "type": "aux",
          "surface": "ける",
          "answer": "過去の助動詞・連体形",
          "explanation": "過去の助動詞・連体形",
          "start": 81,
          "end": 83,
          "formInText": "連体形",
          "sectionId": "s1"
        },
        {
          "id": "particle-s1-14",
          "type": "particle",
          "surface": "を",
          "answer": "格助詞（対象）",
          "explanation": "格助詞（対象）",
          "start": 84,
          "end": 85,
          "particleQuestionType": "translation",
          "sectionId": "s1"
        },
        {
          "id": "particle-s1-15",
          "type": "particle",
          "surface": "は",
          "answer": "係助詞（区別）",
          "explanation": "係助詞（区別）",
          "start": 90,
          "end": 91,
          "particleQuestionType": "translation",
          "sectionId": "s1"
        },
        {
          "id": "particle-s1-16",
          "type": "particle",
          "surface": "ぞ",
          "answer": "係助詞（強意）",
          "explanation": "係助詞（強意）",
          "start": 92,
          "end": 93,
          "particleQuestionType": "translation",
          "sectionId": "s1"
        },
        {
          "id": "particle-s1-17",
          "type": "particle",
          "surface": "と",
          "answer": "格助詞（引用）",
          "explanation": "格助詞（引用）",
          "start": 59,
          "end": 60,
          "particleQuestionType": "translation",
          "sectionId": "s1"
        },
        {
          "id": "particle-s1-18",
          "type": "particle",
          "surface": "なむ",
          "answer": "係助詞（強意）",
          "explanation": "係助詞（強意）",
          "start": 96,
          "end": 98,
          "particleQuestionType": "translation",
          "sectionId": "s1"
        },
        {
          "id": "particle-s1-19",
          "type": "particle",
          "surface": "に",
          "answer": "格助詞（対象）",
          "explanation": "格助詞（対象）",
          "start": 99,
          "end": 100,
          "particleQuestionType": "translation",
          "sectionId": "s1"
        },
        {
          "id": "verb-s1-13",
          "type": "verb",
          "surface": "問ひ",
          "answer": "ハ行四段活用・連用形",
          "explanation": "ハ行四段活用・連用形",
          "start": 100,
          "end": 102,
          "conjugationType": "ハ行四段活用",
          "formInText": "連用形",
          "sectionId": "s1"
        },
        {
          "id": "aux-s1-9",
          "type": "aux",
          "surface": "ける",
          "answer": "過去の助動詞・連体形",
          "explanation": "過去の助動詞・連体形",
          "start": 102,
          "end": 104,
          "formInText": "連体形",
          "sectionId": "s1"
        },
        {
          "id": "adj-s1-2",
          "type": "adj",
          "surface": "多く",
          "answer": "ク活用形容詞・連用形",
          "explanation": "ク活用形容詞・連用形",
          "start": 109,
          "end": 111,
          "conjugationType": "ク活用形容詞",
          "formInText": "連用形",
          "sectionId": "s1"
        },
        {
          "id": "particle-s1-20",
          "type": "particle",
          "surface": "も",
          "answer": "係助詞（同趣）",
          "explanation": "係助詞（同趣）",
          "start": 113,
          "end": 114,
          "particleQuestionType": "translation",
          "sectionId": "s1"
        },
        {
          "id": "verb-s1-14",
          "type": "verb",
          "surface": "更け",
          "answer": "カ行下二段活用・連用形",
          "explanation": "カ行下二段活用・連用形",
          "start": 114,
          "end": 116,
          "conjugationType": "カ行下二段活用",
          "formInText": "連用形",
          "sectionId": "s1"
        },
        {
          "id": "aux-s1-10",
          "type": "aux",
          "surface": "に",
          "answer": "完了の助動詞・連用形",
          "explanation": "完了の助動詞・連用形",
          "start": 116,
          "end": 117,
          "formInText": "連用形",
          "sectionId": "s1"
        },
        {
          "id": "aux-s1-11",
          "type": "aux",
          "surface": "けれ",
          "answer": "過去の助動詞・已然形",
          "explanation": "過去の助動詞・已然形",
          "start": 117,
          "end": 119,
          "formInText": "已然形",
          "sectionId": "s1"
        },
        {
          "id": "particle-s1-21",
          "type": "particle",
          "surface": "ば",
          "answer": "接続助詞（順確原因）",
          "explanation": "接続助詞（順確原因）",
          "start": 70,
          "end": 71,
          "particleQuestionType": "translation",
          "sectionId": "s1"
        },
        {
          "id": "verb-s1-15",
          "type": "verb",
          "surface": "ある",
          "answer": "ラ行変格活用・連体形",
          "explanation": "ラ行変格活用・連体形",
          "start": 123,
          "end": 125,
          "conjugationType": "ラ行変格活用",
          "formInText": "連体形",
          "sectionId": "s1"
        },
        {
          "id": "particle-s1-22",
          "type": "particle",
          "surface": "と",
          "answer": "格助詞（引用）",
          "explanation": "格助詞（引用）",
          "start": 95,
          "end": 96,
          "particleQuestionType": "translation",
          "sectionId": "s1"
        },
        {
          "id": "particle-s1-23",
          "type": "particle",
          "surface": "も",
          "answer": "係助詞（強意）",
          "explanation": "係助詞（強意）",
          "start": 127,
          "end": 128,
          "particleQuestionType": "translation",
          "sectionId": "s1"
        },
        {
          "id": "verb-s1-16",
          "type": "verb",
          "surface": "知ら",
          "answer": "ラ行四段活用・未然形",
          "explanation": "ラ行四段活用・未然形",
          "start": 128,
          "end": 130,
          "conjugationType": "ラ行四段活用",
          "formInText": "未然形",
          "sectionId": "s1"
        },
        {
          "id": "particle-s1-24",
          "type": "particle",
          "surface": "で",
          "answer": "接続助詞（打接）",
          "explanation": "接続助詞（打接）",
          "start": 44,
          "end": 45,
          "particleQuestionType": "translation",
          "sectionId": "s1"
        },
        {
          "id": "particle-s1-25",
          "type": "particle",
          "surface": "さへ",
          "answer": "副助詞（添加）",
          "explanation": "副助詞（添加）",
          "start": 134,
          "end": 136,
          "particleQuestionType": "translation",
          "sectionId": "s1"
        },
        {
          "id": "vocab-s1-4",
          "type": "vocab",
          "surface": "いと",
          "answer": "副詞",
          "explanation": "副詞",
          "start": 136,
          "end": 138,
          "sectionId": "s1"
        },
        {
          "id": "adj-s1-3",
          "type": "adj",
          "surface": "いみじう",
          "answer": "シク活用形容詞・連用形・ウ音便",
          "explanation": "シク活用形容詞・連用形・ウ音便",
          "start": 138,
          "end": 142,
          "conjugationType": "シク活用形容詞",
          "formInText": "ウ音便",
          "sectionId": "s1"
        },
        {
          "id": "verb-s1-17",
          "type": "verb",
          "surface": "鳴り",
          "answer": "ラ行四段活用・連用形",
          "explanation": "ラ行四段活用・連用形",
          "start": 142,
          "end": 144,
          "conjugationType": "ラ行四段活用",
          "formInText": "連用形",
          "sectionId": "s1"
        },
        {
          "id": "particle-s1-26",
          "type": "particle",
          "surface": "も",
          "answer": "係助詞（同趣）",
          "explanation": "係助詞（同趣）",
          "start": 147,
          "end": 148,
          "particleQuestionType": "translation",
          "sectionId": "s1"
        },
        {
          "id": "adj-s1-4",
          "type": "adj",
          "surface": "いたう",
          "answer": "ク活用形容詞・連用形・ウ音便",
          "explanation": "ク活用形容詞・連用形・ウ音便",
          "start": 148,
          "end": 151,
          "conjugationType": "ク活用形容詞",
          "formInText": "ウ音便",
          "sectionId": "s1"
        },
        {
          "id": "verb-s1-18",
          "type": "verb",
          "surface": "降り",
          "answer": "ラ行四段活用・連用形",
          "explanation": "ラ行四段活用・連用形",
          "start": 151,
          "end": 153,
          "conjugationType": "ラ行四段活用",
          "formInText": "連用形",
          "sectionId": "s1"
        },
        {
          "id": "aux-s1-12",
          "type": "aux",
          "surface": "けれ",
          "answer": "過去の助動詞・已然形",
          "explanation": "過去の助動詞・已然形",
          "start": 153,
          "end": 155,
          "formInText": "已然形",
          "sectionId": "s1"
        },
        {
          "id": "particle-s1-27",
          "type": "particle",
          "surface": "ば",
          "answer": "接続助詞（順確原因）",
          "explanation": "接続助詞（順確原因）",
          "start": 119,
          "end": 120,
          "particleQuestionType": "translation",
          "sectionId": "s1"
        },
        {
          "id": "adj-s1-5",
          "type": "adj",
          "surface": "あばらなる",
          "answer": "ナリ活用形容動詞・連体形",
          "explanation": "ナリ活用形容動詞・連体形",
          "start": 158,
          "end": 163,
          "conjugationType": "ナリ活用形容動詞",
          "formInText": "連体形",
          "sectionId": "s1"
        },
        {
          "id": "particle-s1-28",
          "type": "particle",
          "surface": "に",
          "answer": "格助詞（場所）",
          "explanation": "格助詞（場所）",
          "start": 164,
          "end": 165,
          "particleQuestionType": "translation",
          "sectionId": "s1"
        },
        {
          "id": "particle-s1-29",
          "type": "particle",
          "surface": "を",
          "answer": "格助詞（対象）",
          "explanation": "格助詞（対象）",
          "start": 167,
          "end": 168,
          "particleQuestionType": "translation",
          "sectionId": "s1"
        },
        {
          "id": "particle-s1-30",
          "type": "particle",
          "surface": "ば",
          "answer": "係助詞（区別）",
          "explanation": "係助詞（区別）",
          "start": 155,
          "end": 156,
          "particleQuestionType": "translation",
          "sectionId": "s1"
        },
        {
          "id": "particle-s1-31",
          "type": "particle",
          "surface": "に",
          "answer": "格助詞（場所）",
          "explanation": "格助詞（場所）",
          "start": 170,
          "end": 171,
          "particleQuestionType": "translation",
          "sectionId": "s1"
        },
        {
          "id": "verb-s1-19",
          "type": "verb",
          "surface": "押し入れ",
          "answer": "ラ行下二段活用・連用形",
          "explanation": "ラ行下二段活用・連用形",
          "start": 171,
          "end": 175,
          "conjugationType": "ラ行下二段活用",
          "formInText": "連用形",
          "sectionId": "s1"
        },
        {
          "id": "particle-s1-32",
          "type": "particle",
          "surface": "て",
          "answer": "接続助詞（単純）",
          "explanation": "接続助詞（単純）",
          "start": 65,
          "end": 66,
          "particleQuestionType": "translation",
          "sectionId": "s1"
        },
        {
          "id": "particle-s1-33",
          "type": "particle",
          "surface": "を",
          "answer": "格助詞（対象）",
          "explanation": "格助詞（対象）",
          "start": 184,
          "end": 185,
          "particleQuestionType": "translation",
          "sectionId": "s1"
        },
        {
          "id": "verb-s1-20",
          "type": "verb",
          "surface": "負ひ",
          "answer": "ハ行四段活用・連用形",
          "explanation": "ハ行四段活用・連用形",
          "start": 185,
          "end": 187,
          "conjugationType": "ハ行四段活用",
          "formInText": "連用形",
          "sectionId": "s1"
        },
        {
          "id": "particle-s1-34",
          "type": "particle",
          "surface": "て",
          "answer": "接続助詞（単純）",
          "explanation": "接続助詞（単純）",
          "start": 175,
          "end": 176,
          "particleQuestionType": "translation",
          "sectionId": "s1"
        },
        {
          "id": "particle-s1-35",
          "type": "particle",
          "surface": "に",
          "answer": "格助詞（場所）",
          "explanation": "格助詞（場所）",
          "start": 190,
          "end": 191,
          "particleQuestionType": "translation",
          "sectionId": "s1"
        },
        {
          "id": "verb-s1-21",
          "type": "verb",
          "surface": "居り",
          "answer": "ラ行変格活用・終止形",
          "explanation": "ラ行変格活用・終止形",
          "start": 191,
          "end": 193,
          "conjugationType": "ラ行変格活用",
          "formInText": "終止形",
          "sectionId": "s1"
        }
      ]
    },
    {
      "id": "s2",
      "title": "第二段",
      "text": "はや夜も明けなむと思ひつつ居たりけるに、\n鬼はや一口に食ひてけり。\n「あなや。」と言ひけれど、\n神鳴る騒ぎにえ聞かざりけり。\nやうやう夜も明けゆくに、\n見れば、率て来し女もなし。\n足ずりをして泣けどもかひなし。\n　白玉か何ぞと人の問ひしとき\n　露と答へて消えなましものを",
      "modern": "早く夜が明けてほしいと思いながら座っていたところ、（その間に）鬼が（女を）たちまち一口で食ってしまった。（女は）「あれぇ。」と言ったが、雷が鳴る騒がしさに（男は女の悲鳴を）聞くことができなかった。だんだん夜も明けていくので、（蔵の中を）見ると、連れてきた女はいない。（男は）地だんだを踏んでくやしがって泣くけれどもどうしようもない。\n「（あれは）真珠かしら、何かしら。」とあの人が尋ねたとき、「露だよ。」と答えて、（露と同じように私も）消えてしまえばよかったのに。（そうしたらこんな悲しみもなかったであろうに。）",
      "notes": "",
      "targets": [
        {
          "id": "vocab-s1-5",
          "type": "vocab",
          "surface": "はや",
          "answer": "副詞",
          "explanation": "副詞",
          "start": 0,
          "end": 2,
          "sectionId": "s2"
        },
        {
          "id": "particle-s1-36",
          "type": "particle",
          "surface": "も",
          "answer": "係助詞（強意）",
          "explanation": "係助詞（強意）",
          "start": 3,
          "end": 4,
          "particleQuestionType": "translation",
          "sectionId": "s2"
        },
        {
          "id": "verb-s1-22",
          "type": "verb",
          "surface": "明け",
          "answer": "カ行下二段活用・未然形",
          "explanation": "カ行下二段活用・未然形",
          "start": 4,
          "end": 6,
          "conjugationType": "カ行下二段活用",
          "formInText": "未然形",
          "sectionId": "s2"
        },
        {
          "id": "particle-s1-37",
          "type": "particle",
          "surface": "なむ",
          "answer": "終助詞（願望）",
          "explanation": "終助詞（願望）",
          "start": 6,
          "end": 8,
          "particleQuestionType": "translation",
          "sectionId": "s2"
        },
        {
          "id": "particle-s1-38",
          "type": "particle",
          "surface": "と",
          "answer": "格助詞（引用）",
          "explanation": "格助詞（引用）",
          "start": 8,
          "end": 9,
          "particleQuestionType": "translation",
          "sectionId": "s2"
        },
        {
          "id": "verb-s1-23",
          "type": "verb",
          "surface": "思ひ",
          "answer": "ハ行四段活用・連用形",
          "explanation": "ハ行四段活用・連用形",
          "start": 9,
          "end": 11,
          "conjugationType": "ハ行四段活用",
          "formInText": "連用形",
          "sectionId": "s2"
        },
        {
          "id": "particle-s1-39",
          "type": "particle",
          "surface": "つつ",
          "answer": "接続助詞（並行）",
          "explanation": "接続助詞（並行）",
          "start": 11,
          "end": 13,
          "particleQuestionType": "translation",
          "sectionId": "s2"
        },
        {
          "id": "verb-s1-24",
          "type": "verb",
          "surface": "居",
          "answer": "ワ行上一段活用・連用形",
          "explanation": "ワ行上一段活用・連用形",
          "start": 13,
          "end": 14,
          "conjugationType": "ワ行上一段活用",
          "formInText": "連用形",
          "sectionId": "s2"
        },
        {
          "id": "aux-s1-13",
          "type": "aux",
          "surface": "たり",
          "answer": "存続の助動詞・連用形",
          "explanation": "存続の助動詞・連用形",
          "start": 14,
          "end": 16,
          "formInText": "連用形",
          "sectionId": "s2"
        },
        {
          "id": "aux-s1-14",
          "type": "aux",
          "surface": "ける",
          "answer": "過去の助動詞・連体形",
          "explanation": "過去の助動詞・連体形",
          "start": 16,
          "end": 18,
          "formInText": "連体形",
          "sectionId": "s2"
        },
        {
          "id": "particle-s1-40",
          "type": "particle",
          "surface": "に",
          "answer": "接続助詞（単純）",
          "explanation": "接続助詞（単純）",
          "start": 18,
          "end": 19,
          "particleQuestionType": "translation",
          "sectionId": "s2"
        },
        {
          "id": "vocab-s1-6",
          "type": "vocab",
          "surface": "はや",
          "answer": "副詞",
          "explanation": "副詞",
          "start": 22,
          "end": 24,
          "sectionId": "s2"
        },
        {
          "id": "particle-s1-41",
          "type": "particle",
          "surface": "に",
          "answer": "格助詞（手段）",
          "explanation": "格助詞（手段）",
          "start": 26,
          "end": 27,
          "particleQuestionType": "translation",
          "sectionId": "s2"
        },
        {
          "id": "verb-s1-25",
          "type": "verb",
          "surface": "食ひ",
          "answer": "ハ行四段活用・連用形",
          "explanation": "ハ行四段活用・連用形",
          "start": 27,
          "end": 29,
          "conjugationType": "ハ行四段活用",
          "formInText": "連用形",
          "sectionId": "s2"
        },
        {
          "id": "aux-s1-15",
          "type": "aux",
          "surface": "て",
          "answer": "完了の助動詞・連用形",
          "explanation": "完了の助動詞・連用形",
          "start": 29,
          "end": 30,
          "formInText": "連用形",
          "sectionId": "s2"
        },
        {
          "id": "aux-s1-16",
          "type": "aux",
          "surface": "けり",
          "answer": "過去の助動詞・終止形",
          "explanation": "過去の助動詞・終止形",
          "start": 30,
          "end": 32,
          "formInText": "終止形",
          "sectionId": "s2"
        },
        {
          "id": "verb-s1-26",
          "type": "verb",
          "surface": "あな",
          "answer": "感動詞",
          "explanation": "感動詞",
          "start": 35,
          "end": 37,
          "conjugationType": "",
          "formInText": "感動詞",
          "sectionId": "s2"
        },
        {
          "id": "particle-s1-42",
          "type": "particle",
          "surface": "や",
          "answer": "間投助詞（詠嘆）",
          "explanation": "間投助詞（詠嘆）",
          "start": 1,
          "end": 2,
          "particleQuestionType": "translation",
          "sectionId": "s2"
        },
        {
          "id": "particle-s1-43",
          "type": "particle",
          "surface": "と",
          "answer": "格助詞（引用）",
          "explanation": "格助詞（引用）",
          "start": 40,
          "end": 41,
          "particleQuestionType": "translation",
          "sectionId": "s2"
        },
        {
          "id": "verb-s1-27",
          "type": "verb",
          "surface": "言ひ",
          "answer": "ハ行四段活用・連用形",
          "explanation": "ハ行四段活用・連用形",
          "start": 41,
          "end": 43,
          "conjugationType": "ハ行四段活用",
          "formInText": "連用形",
          "sectionId": "s2"
        },
        {
          "id": "aux-s1-17",
          "type": "aux",
          "surface": "けれ",
          "answer": "過去の助動詞・已然形",
          "explanation": "過去の助動詞・已然形",
          "start": 43,
          "end": 45,
          "formInText": "已然形",
          "sectionId": "s2"
        },
        {
          "id": "particle-s1-44",
          "type": "particle",
          "surface": "ど",
          "answer": "接続助詞（逆確）",
          "explanation": "接続助詞（逆確）",
          "start": 45,
          "end": 46,
          "particleQuestionType": "translation",
          "sectionId": "s2"
        },
        {
          "id": "verb-s1-28",
          "type": "verb",
          "surface": "鳴る",
          "answer": "ラ行四段活用・連体形",
          "explanation": "ラ行四段活用・連体形",
          "start": 49,
          "end": 51,
          "conjugationType": "ラ行四段活用",
          "formInText": "連体形",
          "sectionId": "s2"
        },
        {
          "id": "particle-s1-45",
          "type": "particle",
          "surface": "に",
          "answer": "格助詞（原因）",
          "explanation": "格助詞（原因）",
          "start": 53,
          "end": 54,
          "particleQuestionType": "translation",
          "sectionId": "s2"
        },
        {
          "id": "vocab-s1-7",
          "type": "vocab",
          "surface": "え",
          "answer": "副詞",
          "explanation": "副詞",
          "start": 54,
          "end": 55,
          "sectionId": "s2"
        },
        {
          "id": "verb-s1-29",
          "type": "verb",
          "surface": "聞か",
          "answer": "カ行四段活用・未然形",
          "explanation": "カ行四段活用・未然形",
          "start": 55,
          "end": 57,
          "conjugationType": "カ行四段活用",
          "formInText": "未然形",
          "sectionId": "s2"
        },
        {
          "id": "aux-s1-18",
          "type": "aux",
          "surface": "ざり",
          "answer": "打消の助動詞・連用形",
          "explanation": "打消の助動詞・連用形",
          "start": 57,
          "end": 59,
          "formInText": "連用形",
          "sectionId": "s2"
        },
        {
          "id": "aux-s1-19",
          "type": "aux",
          "surface": "けり",
          "answer": "過去の助動詞・終止形",
          "explanation": "過去の助動詞・終止形",
          "start": 59,
          "end": 61,
          "formInText": "終止形",
          "sectionId": "s2"
        },
        {
          "id": "vocab-s1-8",
          "type": "vocab",
          "surface": "やうやう",
          "answer": "副詞",
          "explanation": "副詞",
          "start": 63,
          "end": 67,
          "sectionId": "s2"
        },
        {
          "id": "particle-s1-46",
          "type": "particle",
          "surface": "も",
          "answer": "係助詞（強意）",
          "explanation": "係助詞（強意）",
          "start": 68,
          "end": 69,
          "particleQuestionType": "translation",
          "sectionId": "s2"
        },
        {
          "id": "verb-s1-30",
          "type": "verb",
          "surface": "明けゆく",
          "answer": "カ行四段活用・連体形",
          "explanation": "カ行四段活用・連体形",
          "start": 69,
          "end": 73,
          "conjugationType": "カ行四段活用",
          "formInText": "連体形",
          "sectionId": "s2"
        },
        {
          "id": "particle-s1-47",
          "type": "particle",
          "surface": "に",
          "answer": "接続助詞（順確）",
          "explanation": "接続助詞（順確）",
          "start": 73,
          "end": 74,
          "particleQuestionType": "translation",
          "sectionId": "s2"
        },
        {
          "id": "verb-s1-31",
          "type": "verb",
          "surface": "見れ",
          "answer": "マ行上一段活用・已然形",
          "explanation": "マ行上一段活用・已然形",
          "start": 76,
          "end": 78,
          "conjugationType": "マ行上一段活用",
          "formInText": "已然形",
          "sectionId": "s2"
        },
        {
          "id": "particle-s1-48",
          "type": "particle",
          "surface": "ば",
          "answer": "接続助詞（順確偶然）",
          "explanation": "接続助詞（順確偶然）",
          "start": 78,
          "end": 79,
          "particleQuestionType": "translation",
          "sectionId": "s2"
        },
        {
          "id": "verb-s1-32",
          "type": "verb",
          "surface": "率",
          "answer": "ワ行上一段活用・連用形",
          "explanation": "ワ行上一段活用・連用形",
          "start": 80,
          "end": 81,
          "conjugationType": "ワ行上一段活用",
          "formInText": "連用形",
          "sectionId": "s2"
        },
        {
          "id": "particle-s1-49",
          "type": "particle",
          "surface": "て",
          "answer": "接続助詞（単純）",
          "explanation": "接続助詞（単純）",
          "start": 81,
          "end": 82,
          "particleQuestionType": "translation",
          "sectionId": "s2"
        },
        {
          "id": "verb-s1-33",
          "type": "verb",
          "surface": "来",
          "answer": "カ行変格活用・未然形",
          "explanation": "カ行変格活用・未然形",
          "start": 82,
          "end": 83,
          "conjugationType": "カ行変格活用",
          "formInText": "未然形",
          "sectionId": "s2"
        },
        {
          "id": "aux-s1-20",
          "type": "aux",
          "surface": "し",
          "answer": "過去の助動詞・連体形",
          "explanation": "過去の助動詞・連体形",
          "start": 83,
          "end": 84,
          "formInText": "連体形",
          "sectionId": "s2"
        },
        {
          "id": "particle-s1-50",
          "type": "particle",
          "surface": "も",
          "answer": "係助詞（強意）",
          "explanation": "係助詞（強意）",
          "start": 85,
          "end": 86,
          "particleQuestionType": "translation",
          "sectionId": "s2"
        },
        {
          "id": "adj-s1-6",
          "type": "adj",
          "surface": "なし",
          "answer": "ク活用形容詞・終止形",
          "explanation": "ク活用形容詞・終止形",
          "start": 86,
          "end": 88,
          "conjugationType": "ク活用形容詞",
          "formInText": "終止形",
          "sectionId": "s2"
        },
        {
          "id": "particle-s1-51",
          "type": "particle",
          "surface": "を",
          "answer": "格助詞（対象）",
          "explanation": "格助詞（対象）",
          "start": 93,
          "end": 94,
          "particleQuestionType": "translation",
          "sectionId": "s2"
        },
        {
          "id": "verb-s1-34",
          "type": "verb",
          "surface": "し",
          "answer": "サ行変格活用・連用形",
          "explanation": "サ行変格活用・連用形",
          "start": 87,
          "end": 88,
          "conjugationType": "サ行変格活用",
          "formInText": "連用形",
          "sectionId": "s2"
        },
        {
          "id": "particle-s1-52",
          "type": "particle",
          "surface": "て",
          "answer": "接続助詞（単純）",
          "explanation": "接続助詞（単純）",
          "start": 95,
          "end": 96,
          "particleQuestionType": "translation",
          "sectionId": "s2"
        },
        {
          "id": "verb-s1-35",
          "type": "verb",
          "surface": "泣け",
          "answer": "カ行四段活用・已然形",
          "explanation": "カ行四段活用・已然形",
          "start": 96,
          "end": 98,
          "conjugationType": "カ行四段活用",
          "formInText": "已然形",
          "sectionId": "s2"
        },
        {
          "id": "particle-s1-53",
          "type": "particle",
          "surface": "ども",
          "answer": "接続助詞（逆確）",
          "explanation": "接続助詞（逆確）",
          "start": 98,
          "end": 100,
          "particleQuestionType": "translation",
          "sectionId": "s2"
        },
        {
          "id": "adj-s1-7",
          "type": "adj",
          "surface": "かひなし",
          "answer": "ク活用形容詞・終止形",
          "explanation": "ク活用形容詞・終止形",
          "start": 100,
          "end": 104,
          "conjugationType": "ク活用形容詞",
          "formInText": "終止形",
          "sectionId": "s2"
        },
        {
          "id": "particle-s1-54",
          "type": "particle",
          "surface": "か",
          "answer": "係助詞（疑問）",
          "explanation": "係助詞（疑問）",
          "start": 56,
          "end": 57,
          "particleQuestionType": "translation",
          "sectionId": "s2"
        },
        {
          "id": "particle-s1-55",
          "type": "particle",
          "surface": "ぞ",
          "answer": "係助詞（強意）",
          "explanation": "係助詞（強意）",
          "start": 111,
          "end": 112,
          "particleQuestionType": "translation",
          "sectionId": "s2"
        },
        {
          "id": "particle-s1-56",
          "type": "particle",
          "surface": "と",
          "answer": "格助詞（引用）",
          "explanation": "格助詞（引用）",
          "start": 112,
          "end": 113,
          "particleQuestionType": "translation",
          "sectionId": "s2"
        },
        {
          "id": "particle-s1-57",
          "type": "particle",
          "surface": "の",
          "answer": "格助詞（主格）",
          "explanation": "格助詞（主格）",
          "start": 114,
          "end": 115,
          "particleQuestionType": "translation",
          "sectionId": "s2"
        },
        {
          "id": "verb-s1-36",
          "type": "verb",
          "surface": "問ひ",
          "answer": "ハ行四段活用・連用形",
          "explanation": "ハ行四段活用・連用形",
          "start": 115,
          "end": 117,
          "conjugationType": "ハ行四段活用",
          "formInText": "連用形",
          "sectionId": "s2"
        },
        {
          "id": "aux-s1-21",
          "type": "aux",
          "surface": "し",
          "answer": "過去の助動詞・連体形",
          "explanation": "過去の助動詞・連体形",
          "start": 94,
          "end": 95,
          "formInText": "連体形",
          "sectionId": "s2"
        },
        {
          "id": "particle-s1-58",
          "type": "particle",
          "surface": "と",
          "answer": "格助詞（引用）",
          "explanation": "格助詞（引用）",
          "start": 118,
          "end": 119,
          "particleQuestionType": "translation",
          "sectionId": "s2"
        },
        {
          "id": "verb-s1-37",
          "type": "verb",
          "surface": "答へ",
          "answer": "ハ行下二段活用・連用形",
          "explanation": "ハ行下二段活用・連用形",
          "start": 124,
          "end": 126,
          "conjugationType": "ハ行下二段活用",
          "formInText": "連用形",
          "sectionId": "s2"
        },
        {
          "id": "particle-s1-59",
          "type": "particle",
          "surface": "て",
          "answer": "接続助詞（単純）",
          "explanation": "接続助詞（単純）",
          "start": 126,
          "end": 127,
          "particleQuestionType": "translation",
          "sectionId": "s2"
        },
        {
          "id": "verb-s1-38",
          "type": "verb",
          "surface": "消え",
          "answer": "ヤ行下二段活用・連用形",
          "explanation": "ヤ行下二段活用・連用形",
          "start": 127,
          "end": 129,
          "conjugationType": "ヤ行下二段活用",
          "formInText": "連用形",
          "sectionId": "s2"
        },
        {
          "id": "aux-s1-22",
          "type": "aux",
          "surface": "な",
          "answer": "強意の助動詞・未然形",
          "explanation": "強意の助動詞・未然形",
          "start": 6,
          "end": 7,
          "formInText": "未然形",
          "sectionId": "s2"
        },
        {
          "id": "aux-s1-23",
          "type": "aux",
          "surface": "まし",
          "answer": "実現不可能な希望の助動詞・連体形",
          "explanation": "実現不可能な希望の助動詞・連体形",
          "start": 130,
          "end": 132,
          "formInText": "連体形",
          "sectionId": "s2"
        },
        {
          "id": "particle-s1-60",
          "type": "particle",
          "surface": "ものを",
          "answer": "接続助詞（詠嘆）",
          "explanation": "接続助詞（詠嘆）",
          "start": 132,
          "end": 135,
          "particleQuestionType": "translation",
          "sectionId": "s2"
        }
      ]
    },
    {
      "id": "s3",
      "title": "第三段",
      "text": "これは、二条の后の、いとこの女御の御もとに、\n仕うまつるやうにて居たまへりけるを、\nかたちのいとめでたくおはしければ、\n盗みて負ひて出でたりけるを、\n御兄人堀河の大臣、太郎国経の大納言、\nまだ下﨟にて内裏へ参りたまふに、\nいみじう泣く人あるを聞きつけて、\nとどめて取り返したまうてけり。\nそれを、かく鬼とは言ふなりけり。\nまだいと若うて、后のただにおはしけるときとや。",
      "modern": "この話は、二条の后が、いとこの女御のおそばに、（女房として）お仕え申し上げるようなかたちでおいでになっていたが、（后は）容貌がとても美しくていらっしゃったので、（男が）盗み出して背負って出ていったところ、（后の）兄上である、堀河大臣基経と、ご長男の国経大納言が、まだ官位も低い者であって、参内なさるときに、ひどく泣く人がいるのを聞きつけて、引きとどめて取り返しなさった。それを、このように鬼と言うのであった。（后が）まだとても若く、后が入内なさる以前のことだったということだ。",
      "notes": "",
      "targets": [
        {
          "id": "particle-s1-61",
          "type": "particle",
          "surface": "は",
          "answer": "係助詞（区別）",
          "explanation": "係助詞（区別）",
          "start": 2,
          "end": 3,
          "particleQuestionType": "translation",
          "sectionId": "s3"
        },
        {
          "id": "particle-s1-62",
          "type": "particle",
          "surface": "の",
          "answer": "格助詞（主格）",
          "explanation": "格助詞（主格）",
          "start": 6,
          "end": 7,
          "particleQuestionType": "translation",
          "sectionId": "s3"
        },
        {
          "id": "particle-s1-63",
          "type": "particle",
          "surface": "の",
          "answer": "格助詞（連体）",
          "explanation": "格助詞（連体）",
          "start": 8,
          "end": 9,
          "particleQuestionType": "translation",
          "sectionId": "s3"
        },
        {
          "id": "particle-s1-64",
          "type": "particle",
          "surface": "の",
          "answer": "格助詞（連体）",
          "explanation": "格助詞（連体）",
          "start": 13,
          "end": 14,
          "particleQuestionType": "translation",
          "sectionId": "s3"
        },
        {
          "id": "particle-s1-65",
          "type": "particle",
          "surface": "に",
          "answer": "格助詞（場所）",
          "explanation": "格助詞（場所）",
          "start": 20,
          "end": 21,
          "particleQuestionType": "translation",
          "sectionId": "s3"
        },
        {
          "id": "verb-s1-39",
          "type": "verb",
          "surface": "仕うまつる",
          "answer": "ラ行四段活用・連体形・謙譲",
          "explanation": "ラ行四段活用・連体形・謙譲",
          "start": 23,
          "end": 28,
          "conjugationType": "ラ行四段活用",
          "formInText": "謙譲",
          "sectionId": "s3"
        },
        {
          "id": "aux-s1-24",
          "type": "aux",
          "surface": "やうに",
          "answer": "比況の助動詞・連用形",
          "explanation": "比況の助動詞・連用形",
          "start": 28,
          "end": 31,
          "formInText": "連用形",
          "sectionId": "s3"
        },
        {
          "id": "particle-s1-66",
          "type": "particle",
          "surface": "て",
          "answer": "接続助詞（単純）",
          "explanation": "接続助詞（単純）",
          "start": 31,
          "end": 32,
          "particleQuestionType": "translation",
          "sectionId": "s3"
        },
        {
          "id": "verb-s1-40",
          "type": "verb",
          "surface": "居",
          "answer": "ワ行上一段活用・連用形",
          "explanation": "ワ行上一段活用・連用形",
          "start": 32,
          "end": 33,
          "conjugationType": "ワ行上一段活用",
          "formInText": "連用形",
          "sectionId": "s3"
        },
        {
          "id": "verb-s1-41",
          "type": "verb",
          "surface": "たまへ",
          "answer": "ハ行四段活用・已然形・尊敬・補助",
          "explanation": "ハ行四段活用・已然形・尊敬・補助",
          "start": 33,
          "end": 36,
          "conjugationType": "ハ行四段活用",
          "formInText": "補助",
          "sectionId": "s3"
        },
        {
          "id": "aux-s1-25",
          "type": "aux",
          "surface": "り",
          "answer": "存続の助動詞・連用形",
          "explanation": "存続の助動詞・連用形",
          "start": 36,
          "end": 37,
          "formInText": "連用形",
          "sectionId": "s3"
        },
        {
          "id": "aux-s1-26",
          "type": "aux",
          "surface": "ける",
          "answer": "過去の助動詞・連体形",
          "explanation": "過去の助動詞・連体形",
          "start": 37,
          "end": 39,
          "formInText": "連体形",
          "sectionId": "s3"
        },
        {
          "id": "particle-s1-67",
          "type": "particle",
          "surface": "を",
          "answer": "接続助詞（単純）",
          "explanation": "接続助詞（単純）",
          "start": 39,
          "end": 40,
          "particleQuestionType": "translation",
          "sectionId": "s3"
        },
        {
          "id": "particle-s1-68",
          "type": "particle",
          "surface": "の",
          "answer": "格助詞（主格）",
          "explanation": "格助詞（主格）",
          "start": 16,
          "end": 17,
          "particleQuestionType": "translation",
          "sectionId": "s3"
        },
        {
          "id": "vocab-s1-9",
          "type": "vocab",
          "surface": "いと",
          "answer": "副詞",
          "explanation": "副詞",
          "start": 10,
          "end": 12,
          "sectionId": "s3"
        },
        {
          "id": "adj-s1-8",
          "type": "adj",
          "surface": "めでたく",
          "answer": "ク活用形容詞・連用形",
          "explanation": "ク活用形容詞・連用形",
          "start": 48,
          "end": 52,
          "conjugationType": "ク活用形容詞",
          "formInText": "連用形",
          "sectionId": "s3"
        },
        {
          "id": "verb-s1-42",
          "type": "verb",
          "surface": "おはし",
          "answer": "サ行変格活用・連用形・尊敬・補助",
          "explanation": "サ行変格活用・連用形・尊敬・補助",
          "start": 52,
          "end": 55,
          "conjugationType": "サ行変格活用",
          "formInText": "補助",
          "sectionId": "s3"
        },
        {
          "id": "aux-s1-27",
          "type": "aux",
          "surface": "けれ",
          "answer": "過去の助動詞・已然形",
          "explanation": "過去の助動詞・已然形",
          "start": 55,
          "end": 57,
          "formInText": "已然形",
          "sectionId": "s3"
        },
        {
          "id": "particle-s1-69",
          "type": "particle",
          "surface": "ば",
          "answer": "接続助詞（順確原因）",
          "explanation": "接続助詞（順確原因）",
          "start": 57,
          "end": 58,
          "particleQuestionType": "translation",
          "sectionId": "s3"
        },
        {
          "id": "verb-s1-43",
          "type": "verb",
          "surface": "盗み",
          "answer": "マ行四段活用・連用形",
          "explanation": "マ行四段活用・連用形",
          "start": 60,
          "end": 62,
          "conjugationType": "マ行四段活用",
          "formInText": "連用形",
          "sectionId": "s3"
        },
        {
          "id": "particle-s1-70",
          "type": "particle",
          "surface": "て",
          "answer": "接続助詞（単純）",
          "explanation": "接続助詞（単純）",
          "start": 62,
          "end": 63,
          "particleQuestionType": "translation",
          "sectionId": "s3"
        },
        {
          "id": "verb-s1-44",
          "type": "verb",
          "surface": "負ひ",
          "answer": "ハ行四段活用・連用形",
          "explanation": "ハ行四段活用・連用形",
          "start": 63,
          "end": 65,
          "conjugationType": "ハ行四段活用",
          "formInText": "連用形",
          "sectionId": "s3"
        },
        {
          "id": "particle-s1-71",
          "type": "particle",
          "surface": "て",
          "answer": "接続助詞（単純）",
          "explanation": "接続助詞（単純）",
          "start": 65,
          "end": 66,
          "particleQuestionType": "translation",
          "sectionId": "s3"
        },
        {
          "id": "verb-s1-45",
          "type": "verb",
          "surface": "出で",
          "answer": "ダ行下二段活用・連用形",
          "explanation": "ダ行下二段活用・連用形",
          "start": 66,
          "end": 68,
          "conjugationType": "ダ行下二段活用",
          "formInText": "連用形",
          "sectionId": "s3"
        },
        {
          "id": "aux-s1-28",
          "type": "aux",
          "surface": "たり",
          "answer": "完了の助動詞・連用形",
          "explanation": "完了の助動詞・連用形",
          "start": 68,
          "end": 70,
          "formInText": "連用形",
          "sectionId": "s3"
        },
        {
          "id": "aux-s1-29",
          "type": "aux",
          "surface": "ける",
          "answer": "過去の助動詞・連体形",
          "explanation": "過去の助動詞・連体形",
          "start": 70,
          "end": 72,
          "formInText": "連体形",
          "sectionId": "s3"
        },
        {
          "id": "particle-s1-72",
          "type": "particle",
          "surface": "を",
          "answer": "接続助詞（単純）",
          "explanation": "接続助詞（単純）",
          "start": 72,
          "end": 73,
          "particleQuestionType": "translation",
          "sectionId": "s3"
        },
        {
          "id": "vocab-s1-10",
          "type": "vocab",
          "surface": "まだ",
          "answer": "副詞",
          "explanation": "副詞",
          "start": 94,
          "end": 96,
          "sectionId": "s3"
        },
        {
          "id": "aux-s1-30",
          "type": "aux",
          "surface": "に",
          "answer": "断定の助動詞・連用形",
          "explanation": "断定の助動詞・連用形",
          "start": 30,
          "end": 31,
          "formInText": "連用形",
          "sectionId": "s3"
        },
        {
          "id": "particle-s1-73",
          "type": "particle",
          "surface": "て",
          "answer": "接続助詞（単純）",
          "explanation": "接続助詞（単純）",
          "start": 99,
          "end": 100,
          "particleQuestionType": "translation",
          "sectionId": "s3"
        },
        {
          "id": "particle-s1-74",
          "type": "particle",
          "surface": "へ",
          "answer": "格助詞（方向）",
          "explanation": "格助詞（方向）",
          "start": 35,
          "end": 36,
          "particleQuestionType": "translation",
          "sectionId": "s3"
        },
        {
          "id": "verb-s1-46",
          "type": "verb",
          "surface": "参り",
          "answer": "ラ行四段活用・連用形・謙譲",
          "explanation": "ラ行四段活用・連用形・謙譲",
          "start": 103,
          "end": 105,
          "conjugationType": "ラ行四段活用",
          "formInText": "謙譲",
          "sectionId": "s3"
        },
        {
          "id": "verb-s1-47",
          "type": "verb",
          "surface": "たまふ",
          "answer": "ハ行四段活用・連体形・尊敬・補助",
          "explanation": "ハ行四段活用・連体形・尊敬・補助",
          "start": 105,
          "end": 108,
          "conjugationType": "ハ行四段活用",
          "formInText": "補助",
          "sectionId": "s3"
        },
        {
          "id": "particle-s1-75",
          "type": "particle",
          "surface": "に",
          "answer": "格助詞（時）",
          "explanation": "格助詞（時）",
          "start": 98,
          "end": 99,
          "particleQuestionType": "translation",
          "sectionId": "s3"
        },
        {
          "id": "adj-s1-9",
          "type": "adj",
          "surface": "いみじう",
          "answer": "シク活用形容詞・連用形・ウ音便",
          "explanation": "シク活用形容詞・連用形・ウ音便",
          "start": 111,
          "end": 115,
          "conjugationType": "シク活用形容詞",
          "formInText": "ウ音便",
          "sectionId": "s3"
        },
        {
          "id": "verb-s1-48",
          "type": "verb",
          "surface": "泣く",
          "answer": "カ行四段活用・連体形",
          "explanation": "カ行四段活用・連体形",
          "start": 115,
          "end": 117,
          "conjugationType": "カ行四段活用",
          "formInText": "連体形",
          "sectionId": "s3"
        },
        {
          "id": "verb-s1-49",
          "type": "verb",
          "surface": "ある",
          "answer": "ラ行変格活用・連体形",
          "explanation": "ラ行変格活用・連体形",
          "start": 118,
          "end": 120,
          "conjugationType": "ラ行変格活用",
          "formInText": "連体形",
          "sectionId": "s3"
        },
        {
          "id": "particle-s1-76",
          "type": "particle",
          "surface": "を",
          "answer": "格助詞（対象）",
          "explanation": "格助詞（対象）",
          "start": 120,
          "end": 121,
          "particleQuestionType": "translation",
          "sectionId": "s3"
        },
        {
          "id": "verb-s1-50",
          "type": "verb",
          "surface": "聞きつけ",
          "answer": "カ行下二段活用・連用形",
          "explanation": "カ行下二段活用・連用形",
          "start": 121,
          "end": 125,
          "conjugationType": "カ行下二段活用",
          "formInText": "連用形",
          "sectionId": "s3"
        },
        {
          "id": "particle-s1-77",
          "type": "particle",
          "surface": "て",
          "answer": "接続助詞（単純）",
          "explanation": "接続助詞（単純）",
          "start": 125,
          "end": 126,
          "particleQuestionType": "translation",
          "sectionId": "s3"
        },
        {
          "id": "verb-s1-51",
          "type": "verb",
          "surface": "とどめ",
          "answer": "マ行下二段活用・連用形",
          "explanation": "マ行下二段活用・連用形",
          "start": 128,
          "end": 131,
          "conjugationType": "マ行下二段活用",
          "formInText": "連用形",
          "sectionId": "s3"
        },
        {
          "id": "particle-s1-78",
          "type": "particle",
          "surface": "て",
          "answer": "接続助詞（単純）",
          "explanation": "接続助詞（単純）",
          "start": 131,
          "end": 132,
          "particleQuestionType": "translation",
          "sectionId": "s3"
        },
        {
          "id": "verb-s1-52",
          "type": "verb",
          "surface": "取り返し",
          "answer": "サ行四段活用・連用形",
          "explanation": "サ行四段活用・連用形",
          "start": 132,
          "end": 136,
          "conjugationType": "サ行四段活用",
          "formInText": "連用形",
          "sectionId": "s3"
        },
        {
          "id": "verb-s1-53",
          "type": "verb",
          "surface": "たまう",
          "answer": "ハ行四段活用・連用形・ウ音便・尊敬・補助",
          "explanation": "ハ行四段活用・連用形・ウ音便・尊敬・補助",
          "start": 136,
          "end": 139,
          "conjugationType": "ハ行四段活用",
          "formInText": "補助",
          "sectionId": "s3"
        },
        {
          "id": "aux-s1-31",
          "type": "aux",
          "surface": "て",
          "answer": "完了の助動詞・連用形",
          "explanation": "完了の助動詞・連用形",
          "start": 139,
          "end": 140,
          "formInText": "連用形",
          "sectionId": "s3"
        },
        {
          "id": "aux-s1-32",
          "type": "aux",
          "surface": "けり",
          "answer": "過去の助動詞・終止形",
          "explanation": "過去の助動詞・終止形",
          "start": 140,
          "end": 142,
          "formInText": "終止形",
          "sectionId": "s3"
        },
        {
          "id": "particle-s1-79",
          "type": "particle",
          "surface": "を",
          "answer": "格助詞（対象）",
          "explanation": "格助詞（対象）",
          "start": 146,
          "end": 147,
          "particleQuestionType": "translation",
          "sectionId": "s3"
        },
        {
          "id": "vocab-s1-11",
          "type": "vocab",
          "surface": "かく",
          "answer": "副詞",
          "explanation": "副詞",
          "start": 148,
          "end": 150,
          "sectionId": "s3"
        },
        {
          "id": "particle-s1-80",
          "type": "particle",
          "surface": "と",
          "answer": "格助詞（引用）",
          "explanation": "格助詞（引用）",
          "start": 11,
          "end": 12,
          "particleQuestionType": "translation",
          "sectionId": "s3"
        },
        {
          "id": "particle-s1-81",
          "type": "particle",
          "surface": "は",
          "answer": "係助詞（区別）",
          "explanation": "係助詞（区別）",
          "start": 53,
          "end": 54,
          "particleQuestionType": "translation",
          "sectionId": "s3"
        },
        {
          "id": "verb-s1-54",
          "type": "verb",
          "surface": "言ふ",
          "answer": "ハ行四段活用・連体形",
          "explanation": "ハ行四段活用・連体形",
          "start": 153,
          "end": 155,
          "conjugationType": "ハ行四段活用",
          "formInText": "連体形",
          "sectionId": "s3"
        },
        {
          "id": "aux-s1-33",
          "type": "aux",
          "surface": "なり",
          "answer": "断定の助動詞・連用形",
          "explanation": "断定の助動詞・連用形",
          "start": 155,
          "end": 157,
          "formInText": "連用形",
          "sectionId": "s3"
        },
        {
          "id": "aux-s1-34",
          "type": "aux",
          "surface": "けり",
          "answer": "過去の助動詞・終止形",
          "explanation": "過去の助動詞・終止形",
          "start": 157,
          "end": 159,
          "formInText": "終止形",
          "sectionId": "s3"
        },
        {
          "id": "vocab-s1-12",
          "type": "vocab",
          "surface": "まだ",
          "answer": "副詞",
          "explanation": "副詞",
          "start": 161,
          "end": 163,
          "sectionId": "s3"
        },
        {
          "id": "vocab-s1-13",
          "type": "vocab",
          "surface": "いと",
          "answer": "副詞",
          "explanation": "副詞",
          "start": 46,
          "end": 48,
          "sectionId": "s3"
        },
        {
          "id": "adj-s1-10",
          "type": "adj",
          "surface": "若う",
          "answer": "ク活用形容詞・連用形・ウ音便",
          "explanation": "ク活用形容詞・連用形・ウ音便",
          "start": 165,
          "end": 167,
          "conjugationType": "ク活用形容詞",
          "formInText": "ウ音便",
          "sectionId": "s3"
        },
        {
          "id": "particle-s1-82",
          "type": "particle",
          "surface": "て",
          "answer": "接続助詞（単純）",
          "explanation": "接続助詞（単純）",
          "start": 167,
          "end": 168,
          "particleQuestionType": "translation",
          "sectionId": "s3"
        },
        {
          "id": "particle-s1-83",
          "type": "particle",
          "surface": "の",
          "answer": "格助詞（主格）",
          "explanation": "格助詞（主格）",
          "start": 45,
          "end": 46,
          "particleQuestionType": "translation",
          "sectionId": "s3"
        },
        {
          "id": "adj-s1-11",
          "type": "adj",
          "surface": "ただに",
          "answer": "ナリ活用形容動詞・連用形",
          "explanation": "ナリ活用形容動詞・連用形",
          "start": 171,
          "end": 174,
          "conjugationType": "ナリ活用形容動詞",
          "formInText": "連用形",
          "sectionId": "s3"
        },
        {
          "id": "verb-s1-55",
          "type": "verb",
          "surface": "おはし",
          "answer": "サ行変格活用・連用形・尊敬・補助",
          "explanation": "サ行変格活用・連用形・尊敬・補助",
          "start": 174,
          "end": 177,
          "conjugationType": "サ行変格活用",
          "formInText": "補助",
          "sectionId": "s3"
        },
        {
          "id": "aux-s1-35",
          "type": "aux",
          "surface": "ける",
          "answer": "過去の助動詞・連体形",
          "explanation": "過去の助動詞・連体形",
          "start": 177,
          "end": 179,
          "formInText": "連体形",
          "sectionId": "s3"
        },
        {
          "id": "vocab-s1-14",
          "type": "vocab",
          "surface": "とや",
          "answer": "連語",
          "explanation": "連語",
          "start": 181,
          "end": 183,
          "sectionId": "s3"
        },
        {
          "id": "vocab-s1-15",
          "type": "vocab",
          "surface": "????",
          "sectionId": "s3",
          "pos": "???",
          "conjugationType": "?",
          "meaning": "?????",
          "detail": "???????????????????",
          "answer": "?????",
          "explanation": "???????????????????"
        }
      ]
    }
  ],
  "normalQuestions": [
    {
      "id": "trans-1",
      "type": "translation",
      "title": "現代語訳①",
      "question": "「女のえ得まじかりける」を訳せ。",
      "targetText": "女のえ得まじかりける",
      "sectionId": "s1",
      "answer": "結婚できそうになかった女。",
      "explanation": ""
    },
    {
      "id": "content-1",
      "type": "content",
      "title": "内容読解①",
      "question": "「女のえ得まじかりけるを」とあるが、結婚できそうになかったのはなぜか。その理由を考えよ。",
      "sectionId": "s1",
      "answer": "女が高貴な人で、男とは身分が違ったため。（別解…将来入内させることも考えて大切に育てられていたため。）",
      "explanation": ""
    },
    {
      "id": "content-2",
      "type": "content",
      "title": "内容読解②",
      "question": "男は、女をどのようにして盗み出したと推測できるか。",
      "sectionId": "s1",
      "answer": "あらかじめ女と打ち合わせをして（従者の手引きによって）二人で逃げた。",
      "explanation": ""
    },
    {
      "id": "content-3",
      "type": "content",
      "title": "内容読解③",
      "question": "女を盗み出したときの男の気持ちはどのようであったか。",
      "sectionId": "s1",
      "answer": "男は長年の思いが叶う喜びと、女を守り一刻も早く逃げなければという責任感・緊張感で興奮していた。",
      "explanation": ""
    },
    {
      "id": "content-4",
      "type": "content",
      "title": "内容読解④",
      "question": "「来けり」と「行きけり」との違いを説明せよ。",
      "sectionId": "s1",
      "answer": "「来けり」は「芥川」に視点を据えて見ていると、こちらへ向かってやってきたという表現、「行きけり」は男の視点から逃げていく方向を見て、そちらに向かって進んでいくという表現である。",
      "explanation": ""
    },
    {
      "id": "trans-2",
      "type": "translation",
      "title": "現代語訳②",
      "question": "「かれは何ぞ。」を現代語訳せよ。",
      "targetText": "かれは何ぞ。",
      "sectionId": "s1",
      "answer": "あれは何ですか。",
      "explanation": ""
    },
    {
      "id": "content-5",
      "type": "content",
      "title": "内容読解⑤",
      "question": "「かれは何ぞ。」という発言から、「女」はどのような人物だと思われるか。",
      "sectionId": "s1",
      "answer": "深窓に暮らす高貴な身分の姫君。",
      "explanation": ""
    },
    {
      "id": "content-6",
      "type": "content",
      "title": "内容読解⑥",
      "question": "男は「かれは何ぞ。」という女の問いに対してどうしたか。",
      "sectionId": "s1",
      "answer": "何も答えなかった。",
      "explanation": ""
    },
    {
      "id": "content-7",
      "type": "content",
      "title": "内容読解⑦",
      "question": "男は「かれは何ぞ。」という女の問いに対して何も答えなかったが、それはなぜか。",
      "sectionId": "s1",
      "answer": "一刻も早く遠くへ逃げたかったので、心に余裕がなかったから。",
      "explanation": ""
    },
    {
      "id": "content-8",
      "type": "content",
      "local": true,
      "title": "内容読解⑧",
      "question": "「夜も更けにければ」は文脈上どこに続くか。かかっていく文節を抜き出せ。思（短答・AI採点なし）",
      "sectionId": "s1",
      "answer": "押し入れて",
      "explanation": ""
    },
    {
      "id": "content-9",
      "type": "content",
      "title": "内容読解⑨",
      "question": "何に加えて「神さへ」と言っているのか。",
      "sectionId": "s1",
      "answer": "行く先が遠く夜も更けてしまったこと。",
      "explanation": ""
    },
    {
      "id": "content-10",
      "type": "content",
      "title": "内容読解⑩",
      "question": "「降りければ」の「ば」を1、「女をば」の「ば」を2として、1と2の違いを文法的に説明せよ。",
      "sectionId": "s1",
      "answer": "1は接続助詞、2は係助詞「は」が濁音化したもの。",
      "explanation": ""
    },
    {
      "id": "content-11",
      "type": "content",
      "title": "内容読解⑪",
      "question": "「男」が武装して戸口にいたのはなぜか。",
      "sectionId": "s1",
      "answer": "女を連れ戻しにくる追っ手から女を守るため。",
      "explanation": ""
    },
    {
      "id": "trans-3",
      "type": "translation",
      "title": "現代語訳③",
      "question": "「はや夜も明けなむ」を現代語訳せよ。",
      "targetText": "はや夜も明けなむ",
      "sectionId": "s2",
      "answer": "早く夜が明けてほしい。",
      "explanation": ""
    },
    {
      "id": "trans-4",
      "type": "translation",
      "title": "現代語訳④",
      "question": "「え聞かざりけり」を主語、目的語を補って現代語訳せよ。",
      "targetText": "え聞かざりけり",
      "sectionId": "s2",
      "answer": "男は女の悲鳴を聞くことができなかった。",
      "explanation": ""
    },
    {
      "id": "content-12",
      "type": "content",
      "local": true,
      "title": "内容読解⑫",
      "question": "「白玉か…」の和歌に用いられている修辞は何か。（短答・AI採点なし）",
      "sectionId": "s2",
      "answer": "縁語",
      "explanation": ""
    },
    {
      "id": "trans-5",
      "type": "translation",
      "title": "現代語訳⑤",
      "question": "「かたちのいとめでたくおはしければ」を現代語訳せよ。",
      "targetText": "かたちのいとめでたくおはしければ",
      "sectionId": "s3",
      "answer": "容貌がとても美しくていらっしゃったので",
      "explanation": ""
    },
    {
      "id": "content-13",
      "type": "content",
      "title": "内容読解⑬",
      "question": "備考の絵巻の中で、本文の描写と異なる描かれ方をしている場面はどこか。",
      "sectionId": "s2",
      "answer": "絵巻左の、鬼に食われる女を見て男が足ずりをしている場面。",
      "explanation": ""
    },
    {
      "id": "trans-6",
      "type": "translation",
      "title": "現代語訳⑥",
      "question": "「え得まじかりける」から分かる、「男」の女に対する心情は？",
      "targetText": "え得まじかりける",
      "sectionId": "s1",
      "answer": "女に何年も求婚し続けるほど、女への強い愛情が深い。",
      "explanation": ""
    },
    {
      "id": "trans-7",
      "type": "translation",
      "title": "現代語訳⑦",
      "question": "第二段落で語られている事の顚末を説明せよ。",
      "targetText": "第二段落で語られている事の顚末",
      "sectionId": "s3",
      "answer": "男は、「いとこの女御」のもとにいた藤原高子（後の二条の后）を盗み出したが、高子の兄たちが取り返した。",
      "explanation": ""
    },
    {
      "id": "trans-8",
      "type": "translation",
      "title": "現代語訳⑧",
      "question": "「足ずりをして」とあるが、ここから男のどのような心情が読み取れるか。",
      "targetText": "足ずりをして",
      "sectionId": "s2",
      "answer": "女を失った悲しみ。鬼の棲む蔵に女を入れてしまったことへの後悔。不本意な現実をどうすることもできないもどかしさ。",
      "explanation": ""
    }
  ],
  "lessonViewPublished": true,
  "lessonViewSections": {
    "s1": {
      "section": {
        "text": "昔、男ありけり。女のえ得まじかりけるを、\n年を経てよばひわたりけるを、からうじて\n盗み出でて、いと暗きに来けり。\n芥川といふ川を率て行きければ、\n草の上に置きたりける露を、\n「かれは何ぞ。」となむ男に問ひける。\n行く先多く、夜も更けにければ、\n鬼ある所とも知らで、\n神さへいといみじう鳴り、\n雨もいたう降りければ、\nあばらなる蔵に、女をば奥に押し入れて、\n男、弓・胡籙を負ひて戸口に居り。",
        "modern": "昔、男がいた。女で手に入れることができそうになかった女を、長年にわたって求婚し続けていたが、やっとのことで盗み出して、とても暗いときに逃げて来た。芥川という川（のほとり）を（女を）連れて行ったところ、草の上に降りていた夜露を、「あれは何ですか。」と（女は）男に尋ねた。行く先が遠く、夜も更けてしまったので、鬼が棲むところとも知らないで、そのうえ雷までもたいそうひどく鳴り、雨も激しく降ったので、荒れてがらんとした蔵に、女を奥の方に押し入れて、男は、弓・胡籙を背負って戸口にいる。",
        "kundoku": ""
      },
      "published": true
    },
    "s2": {
      "section": {
        "text": "はや夜も明けなむと思ひつつ居たりけるに、\n鬼はや一口に食ひてけり。\n「あなや。」と言ひけれど、\n神鳴る騒ぎにえ聞かざりけり。\nやうやう夜も明けゆくに、\n見れば、率て来し女もなし。\n足ずりをして泣けどもかひなし。\n　白玉か何ぞと人の問ひしとき\n　露と答へて消えなましものを",
        "modern": "早く夜が明けてほしいと思いながら座っていたところ、（その間に）鬼が（女を）たちまち一口で食ってしまった。（女は）「あれぇ。」と言ったが、雷が鳴る騒がしさに（男は女の悲鳴を）聞くことができなかった。だんだん夜も明けていくので、（蔵の中を）見ると、連れてきた女はいない。（男は）地だんだを踏んでくやしがって泣くけれどもどうしようもない。\n「（あれは）真珠かしら、何かしら。」とあの人が尋ねたとき、「露だよ。」と答えて、（露と同じように私も）消えてしまえばよかったのに。（そうしたらこんな悲しみもなかったであろうに。）",
        "kundoku": ""
      },
      "published": true
    },
    "s3": {
      "section": {
        "text": "これは、二条の后の、いとこの女御の御もとに、\n仕うまつるやうにて居たまへりけるを、\nかたちのいとめでたくおはしければ、\n盗みて負ひて出でたりけるを、\n御兄人堀河の大臣、太郎国経の大納言、\nまだ下﨟にて内裏へ参りたまふに、\nいみじう泣く人あるを聞きつけて、\nとどめて取り返したまうてけり。\nそれを、かく鬼とは言ふなりけり。\nまだいと若うて、后のただにおはしけるときとや。",
        "modern": "この話は、二条の后が、いとこの女御のおそばに、（女房として）お仕え申し上げるようなかたちでおいでになっていたが、（后は）容貌がとても美しくていらっしゃったので、（男が）盗み出して背負って出ていったところ、（后の）兄上である、堀河大臣基経と、ご長男の国経大納言が、まだ官位も低い者であって、参内なさるときに、ひどく泣く人がいるのを聞きつけて、引きとどめて取り返しなさった。それを、このように鬼と言うのであった。（后が）まだとても若く、后が入内なさる以前のことだったということだ。",
        "kundoku": ""
      },
      "published": true
    }
  }
}
